{
  "flight": "TK775",
  "date": "18-Mar",
  "std_etd": "01:55",
  "destination": "IST",
  "format": "A",
  "items": [
    {
      "awb": "AKH-3082TK",
      "pcs": "2",
      "kgs": "30",
      "description": "BLOOD SAMPLES",
      "reason": "PAYLOAD",
      "class_": "",
      "item": "",
      "trolley": ""
    },
    {
      "awb": "AKH-4780TK",
      "pcs": "1",
      "kgs": "330",
      "description": "INSTMT3071NC L",
      "reason": "PAYLOAD",
      "class_": "",
      "item": "",
      "trolley": ""
    },
    {
      "awb": "AKH-5216TK",
      "pcs": "1",
      "kgs": "132",
      "description": "INSTMT3071NC L",
      "reason": "PAYLOAD",
      "class_": "",
      "item": "",
      "trolley": ""
    },
    {
      "awb": "AKH-5914TK",
      "pcs": "5",
      "kgs": "423",
      "description": "PORTHOLE ASSY",
      "reason": "PAYLOAD",
      "class_": "",
      "item": "",
      "trolley": ""
    },
    {
      "awb": "AKH-7021TK",
      "pcs": "2",
      "kgs": "203.5",
      "description": "CONSOLIDATION",
      "reason": "PAYLOAD",
      "class_": "",
      "item": "",
      "trolley": ""
    }
  ],
  "email_time": "03:23",
  "saved_at": "2026-03-18T03:23:00+04:00",
  "retro_enriched_at": "2026-04-17T18:16:39.238122+04:00",
  "retro_enriched_source": "local_db",
  "enrichment_source": "Flightradar",
  "last_enriched": "2026-04-14T14:54:38.351992+04:00",
  "_tz_fixed": "2026-04-17T14:16:39Z"
}