{
  "flight": "WY683",
  "date": "01-APR",
  "std_etd": "13:55",
  "destination": "RUH",
  "format": "A",
  "items": [
    {
      "awb": "910-18712691",
      "pcs": "3",
      "kgs": "128",
      "description": "TUBES PIPES HS",
      "reason": "DUE TO HIGHT",
      "class_": "",
      "item": "",
      "trolley": ""
    }
  ],
  "email_time": "14:26",
  "saved_at": "2026-04-01T14:26:00+04:00",
  "retro_enriched_at": "2026-04-03T16:39:30.152724+04:00",
  "retro_enriched_source": "AirLabs",
  "enrichment_source": "local_db",
  "last_enriched": "2026-04-11T14:42:51.432180+04:00"
}